<?xml version="1.0" encoding="UTF-8"?>
<!--
Created with Free texture packer v0.6.7 http://free-tex-packer.com
-->
<TextureAtlas imagePath="chica.png" width="522" height="334">
  <SubTexture name="Up0002" x="1" y="1"  width="121" height="160" frameX="-45" frameY="-36" frameWidth="200" frameHeight="200"/>
  <SubTexture name="Down0002" x="124" y="1"  width="131" height="163" frameX="-45" frameY="-33" frameWidth="200" frameHeight="200"/>
  <SubTexture name="Left0002" x="257" y="1"  width="131" height="163" frameX="-45" frameY="-33" frameWidth="200" frameHeight="200"/>
  <SubTexture name="Right0002" x="390" y="1"  width="131" height="163" frameX="-45" frameY="-33" frameWidth="200" frameHeight="200"/>
  <SubTexture name="Up0001" x="1" y="163"  width="121" height="164" frameX="-44" frameY="-32" frameWidth="200" frameHeight="200"/>
  <SubTexture name="Down0001" x="124" y="166"  width="131" height="167" frameX="-44" frameY="-29" frameWidth="200" frameHeight="200"/>
  <SubTexture name="Left0001" x="257" y="166"  width="131" height="167" frameX="-44" frameY="-29" frameWidth="200" frameHeight="200"/>
  <SubTexture name="Right0001" x="390" y="166"  width="131" height="167" frameX="-44" frameY="-29" frameWidth="200" frameHeight="200"/>
</TextureAtlas>